occson/__init__.py
occson/document.py
occson/downloader.py
occson/uploader.py
tests/__init__.py
tests/test_downloader.py
tests/test_uploader.py
occson-1.0.0.dist-info/LICENSE
occson-1.0.0.dist-info/METADATA
occson-1.0.0.dist-info/WHEEL
occson-1.0.0.dist-info/top_level.txt
occson-1.0.0.dist-info/RECORD
